{
  "properties": {
    "name": "国指定文化財"
  },
  "type": "FeatureCollection",
  "features": [{
    "type": "Feature",
    "geometry": {
      "type": "Point",
      "coordinates": [134.24609005451202, 35.50118149702313]
    },
    "properties": {
      "name": "樗谿神社本殿・唐門・拝殿及び弊殿",
      "description": "鳥取東照宮（とっとりとうしょうぐう）は、鳥取県鳥取市にある神社。江戸時代の創建より因幡東照宮（いなばとうしょうぐう）と称され、明治7年（1874年）から平成23年（2011年）までは樗谿神社（おうちだにじんじゃ）と称されていた。 祭神は、主神として東照大権現を祀り、配神として池田忠継・忠雄・光仲・慶徳を合祀する。本殿・拝殿・幣殿・唐門の4棟の建造物は、国の重要文化財に指定されている。\n\n[[https://creativecommons.org/licenses/by-sa/3.0/deed.ja|CC BY-SA 3.0]]\n\n[[https://ja.wikipedia.org/wiki/%E9%B3%A5%E5%8F%96%E6%9D%B1%E7%85%A7%E5%AE%AE|鳥取東照宮 - Wikipedia]]\n"
    }
  }, {
    "type": "Feature",
    "geometry": {
      "type": "Point",
      "coordinates": [134.227145, 35.496137]
    },
    "properties": {
      "name": "百歳祝着（ひゃくさいいわいぎ）",
      "type": "有形民俗文化財",
      "description": "この打掛は、邑美郡吉成村（現鳥取市吉成）の大庄屋の娘、北川こと（天保７年～大正７年）が岩井郡長郷村（現岩美町長郷）の大庄屋、勝山家に嫁ぐときに持参したものである。 年祝には、昔から親類縁者が衣類を贈る習俗があったが、この着衣は娘の長寿を願って嫁入りの際、特別にあつらえて持参させたものである。大庄屋級の晴着として、これが木綿であることは窮迫した江戸末期の時代相を反映しているが、縁起絵にはかなりの比重をかけている。絵柄は、翁・姥・松竹梅・鶴亀など縁起物があしらわれ、背に「百」の文字が白抜きしてある。柄部分の染色は、筒引きで地色の茶は引き染めの草木染めであるが、染料の種類は不明である。製作年代は、江戸時代の末期であるが、製作地及び製作者は不明である。"
    }
  }]
}
